hello_world/__init__.py
hello_world/hello_cdk.py
aws_orbit_hello_world-1.4.0.dist-info/METADATA
aws_orbit_hello_world-1.4.0.dist-info/VERSION
aws_orbit_hello_world-1.4.0.dist-info/WHEEL
aws_orbit_hello_world-1.4.0.dist-info/top_level.txt
aws_orbit_hello_world-1.4.0.dist-info/RECORD
