Metadata-Version: 2.1
Name: aws-orbit-hello-world
Version: 1.4.0
Summary: Minimal Orbit Workbench Plugin.
Home-page: https://github.com/awslabs/aws-orbit-workbench
Author: AWS Professional Services
Author-email: aws-proserve-opensource@amazon.com
License: Apache License 2.0
Project-URL: Org Site, https://aws.amazon.com/professional-services/
Keywords: aws,cdk
Platform: UNKNOWN
Classifier: Development Status :: 4 - Beta
Classifier: Framework :: Jupyter
Classifier: Intended Audience :: Developers
Classifier: Intended Audience :: Information Technology
Classifier: Intended Audience :: Science/Research
Classifier: License :: OSI Approved :: Apache Software License
Classifier: Programming Language :: Python :: 3 :: Only
Classifier: Programming Language :: Python :: 3.7
Classifier: Programming Language :: Python :: 3.8
Classifier: Typing :: Typed
Requires-Python: >=3.7, <3.9
